pyscreenshot/__init__.py
pyscreenshot/about.py
pyscreenshot/childproc.py
pyscreenshot/err.py
pyscreenshot/imcodec.py
pyscreenshot/loader.py
pyscreenshot/tempdir.py
pyscreenshot/tempdir27.py
pyscreenshot/tempexport.py
pyscreenshot/util.py
pyscreenshot/check/__init__.py
pyscreenshot/check/showall.py
pyscreenshot/check/speedtest.py
pyscreenshot/check/versions.py
pyscreenshot/cli/__init__.py
pyscreenshot/cli/grab.py
pyscreenshot/cli/print_backend_version.py
pyscreenshot/examples/__init__.py
pyscreenshot/examples/showgrabbox.py
pyscreenshot/examples/showgrabfullscreen.py
pyscreenshot/plugins/__init__.py
pyscreenshot/plugins/backend.py
pyscreenshot/plugins/gdk3pixbuf.py
pyscreenshot/plugins/gnome_dbus.py
pyscreenshot/plugins/gnome_screenshot.py
pyscreenshot/plugins/gtkpixbuf.py
pyscreenshot/plugins/imagemagick.py
pyscreenshot/plugins/kwin_dbus.py
pyscreenshot/plugins/mac_quartz.py
pyscreenshot/plugins/mac_screencapture.py
pyscreenshot/plugins/maim.py
pyscreenshot/plugins/msswrap.py
pyscreenshot/plugins/pilwrap.py
pyscreenshot/plugins/pyside2_grabwindow.py
pyscreenshot/plugins/pyside_grabwindow.py
pyscreenshot/plugins/qt4grabwindow.py
pyscreenshot/plugins/qt5grabwindow.py
pyscreenshot/plugins/qtpy_grabwindow.py
pyscreenshot/plugins/scrot.py
pyscreenshot/plugins/wxscreen.py
pyscreenshot-2.2.dist-info/LICENSE.txt
pyscreenshot-2.2.dist-info/METADATA
pyscreenshot-2.2.dist-info/WHEEL
pyscreenshot-2.2.dist-info/top_level.txt
pyscreenshot-2.2.dist-info/RECORD
